README.rst
setup.py
le_client/__init__.py
le_client/__main__.py
le_client/acme.py
le_client/keys.py
le_client/request.py
le_client/tests.py
le_client/utils.py
le_client.egg-info/PKG-INFO
le_client.egg-info/SOURCES.txt
le_client.egg-info/dependency_links.txt
le_client.egg-info/entry_points.txt
le_client.egg-info/top_level.txt