Metadata-Version: 1.1
Name: le-client
Version: 0.1
Summary: Yet another simple Let's Encrypt/ACME client
Home-page: https://github.com/drdaeman/le-client
Author: Aleksey Zhukov
Author-email: drdaeman@drdaeman.pp.ru
License: GNU GPLv3+
Platform: UNKNOWN
Classifier: Environment :: Web Environment
Classifier: Intended Audience :: Developers
Classifier: Intended Audience :: System Administrators
Classifier: License :: OSI Approved :: GNU General Public License v3 or later (GPLv3+)
Classifier: Operating System :: OS Independent
Classifier: Programming Language :: Python
Classifier: Programming Language :: Python :: 3
Classifier: Programming Language :: Python :: 3 :: Only
Classifier: Programming Language :: Python :: 3.4
Classifier: Programming Language :: Python :: 3.5
Classifier: Topic :: Internet :: WWW/HTTP
Classifier: Topic :: Security
Classifier: Topic :: Security :: Cryptography
